response_functions/__init__.py
response_functions/common.py
response_functions/dielectric_constants.py
response_functions/hexagonal_boron_nitride.py
response_functions/massless_dirac_fermions.py
response_functions/parabolic_bands.py
response_functions-0.5.0.dist-info/LICENSE
response_functions-0.5.0.dist-info/METADATA
response_functions-0.5.0.dist-info/WHEEL
response_functions-0.5.0.dist-info/RECORD
