Metadata-Version: 2.1
Name: response-functions
Version: 0.5.0
Summary: Package containing response functions for 2D materials and other low-energy models in solid-state physics
License: LGPL-3.0-only
Author: Iacopo Torre
Author-email: iacopo.torre@upc.edu
Requires-Python: >=3.8,<4.0
Classifier: License :: OSI Approved :: GNU Lesser General Public License v3 (LGPLv3)
Classifier: Programming Language :: Python :: 3
Classifier: Programming Language :: Python :: 3.8
Classifier: Programming Language :: Python :: 3.9
Classifier: Programming Language :: Python :: 3.10
Classifier: Programming Language :: Python :: 3.11
Classifier: Programming Language :: Python :: 3.12
Requires-Dist: matplotlib (>=3,<4)
Requires-Dist: mpmath (>=1.3,<2.0)
Requires-Dist: numpy (>=1.18,<2.0)
Requires-Dist: scipy (>=1,<2)
